terminal_colored_print/__init__.py
terminal_colored_print-0.3.0.dist-info/LICENSE
terminal_colored_print-0.3.0.dist-info/METADATA
terminal_colored_print-0.3.0.dist-info/WHEEL
terminal_colored_print-0.3.0.dist-info/top_level.txt
terminal_colored_print-0.3.0.dist-info/RECORD
