Metadata-Version: 2.1
Name: terminal-colored-print
Version: 0.3.0
Summary: A small module that allows to simply decorate strings on Linux terminals
Home-page: https://github.com/framilano/Terminal-Colored-Print
Author: Francesco Milano
Author-email: milano.francesco@protonmail.com
Project-URL: Bug Tracker, https://github.com/framilano/Terminal-Colored-Print/issues
Classifier: Programming Language :: Python :: 2
Classifier: License :: OSI Approved :: MIT License
Classifier: Operating System :: OS Independent
Requires-Python: >=2.7
License-File: LICENSE
